qutip_cuquantum/__init__.py
qutip_cuquantum/callable.py
qutip_cuquantum/family.py
qutip_cuquantum/mixed_dispatch.py
qutip_cuquantum/ode.py
qutip_cuquantum/operator.py
qutip_cuquantum/qobjevo.cpp
qutip_cuquantum/qobjevo.cpython-311-x86_64-linux-gnu.so
qutip_cuquantum/qobjevo.pyx
qutip_cuquantum/state.py
qutip_cuquantum/utils.py
qutip_cuquantum/version.py
qutip_cuquantum-0.1.2.dist-info/METADATA
qutip_cuquantum-0.1.2.dist-info/WHEEL
qutip_cuquantum-0.1.2.dist-info/entry_points.txt
qutip_cuquantum-0.1.2.dist-info/top_level.txt
qutip_cuquantum-0.1.2.dist-info/RECORD
qutip_cuquantum-0.1.2.dist-info/licenses/LICENSE
