Metadata-Version: 2.4
Name: qutip-cuquantum
Version: 0.1.2
Summary: cuQuantum backend for QuTiP
Author-email: Eric Giguère <qutip-admin@googlegroups.com>
License: BSD 3-Clause License
Project-URL: Homepage, https://qutip.org
Project-URL: Bug Tracker, https://github.com/qutip/qutip-cuquantum/issues
Project-URL: Documentation, https://qutip-cuquantum.readthedocs.io/en/latest/
Keywords: quantum,physics,dynamics,gpu,linear-algebra
Classifier: Development Status :: 2 - Pre-Alpha
Classifier: Intended Audience :: Science/Research
Classifier: Programming Language :: Python
Classifier: Programming Language :: Python :: 3
Classifier: Topic :: Scientific/Engineering
Classifier: Operating System :: Unix
Requires-Python: >=3.11
License-File: LICENSE
Requires-Dist: qutip>=5.2.1
Provides-Extra: cuda11
Requires-Dist: cupy-cuda11x; extra == "cuda11"
Requires-Dist: cuquantum-python-cu11; extra == "cuda11"
Provides-Extra: cuda12
Requires-Dist: cupy-cuda12x; extra == "cuda12"
Requires-Dist: cuquantum-python-cu12; extra == "cuda12"
Provides-Extra: tests
Requires-Dist: pytest>=6.0; extra == "tests"
Dynamic: license-file
